armenian_russian_lang_mcp/__init__.py
armenian_russian_lang_mcp/alphabet.md
armenian_russian_lang_mcp/am-rus.dsl
armenian_russian_lang_mcp/install_to_claude.py
armenian_russian_lang_mcp/rus-am.dsl
armenian_russian_lang_mcp/server.py
armenian_russian_lang_mcp/translation.py
armenian_russian_lang_mcp/transliteration.py
armenian_russian_lang_mcp-0.1.0.dist-info/METADATA
armenian_russian_lang_mcp-0.1.0.dist-info/WHEEL
armenian_russian_lang_mcp-0.1.0.dist-info/entry_points.txt
armenian_russian_lang_mcp-0.1.0.dist-info/licenses/LICENSE
armenian_russian_lang_mcp-0.1.0.dist-info/RECORD
