Metadata-Version: 2.4
Name: armenian-russian-lang-mcp
Version: 0.1.0
Summary: MCP server for Armenian-Russian transliteration and translation
Project-URL: Homepage, https://gitlab.com/smoug25/armenian-russian-lang-mcp
Project-URL: Issues, https://gitlab.com/smoug25/armenian-russian-lang-mcp/issues
Project-URL: Documentation, https://gitlab.com/smoug25/armenian-russian-lang-mcp#readme
Author-email: Aleksandr Vorobev <aleksandr@vorobev.dev>
License-Expression: MIT
License-File: LICENSE
Keywords: armenian,claude,mcp,russian,translation,transliteration
Classifier: Development Status :: 4 - Beta
Classifier: Intended Audience :: Developers
Classifier: License :: OSI Approved :: MIT License
Classifier: Operating System :: OS Independent
Classifier: Programming Language :: Python :: 3
Classifier: Topic :: Text Processing :: Linguistic
Requires-Python: >=3.12
Requires-Dist: mcp[cli]>=0.1.0
